{
  "count": 14,
  "articles": [
    {
      "article_id": "bbad177ee65d0c59",
      "title": "Sudeep Pharma Raises Rs 268 Crore From Anchor Investors Ahead Of IPO",
      "body": "Sudeep Pharma Pvt. Ltd. announced that it garnered Rs 268.5 crore from anchor investors on Thursday, ahead of its initial public offer IPO, which begins on Friday, as per an exchange filing on BSE. 1753 chars",
      "source": "Ndtvprofit.com",
      "timestamp": "2025-11-22T00:25:42.697842",
      "url": "https://www.ndtvprofit.com/ipos/sudeep-pharma-raises-rs-268-crore-from-anchor-investors-ahead-of-ipo",
      "raw_text": "Sudeep Pharma Raises Rs 268 Crore From Anchor Investors Ahead Of IPO. Sudeep Pharma Pvt. Ltd. announced that it garnered Rs 268.5 crore from anchor investors on Thursday, ahead of its initial public offer IPO, which begins on Friday, as per an exchange filing on BSE. 1753 chars",
      "tickers_mentioned": "PSA",
      "sentiment": "neutral",
      "ticker_contexts": {
        "PSA": []
      },
      "features": {
        "entities": {
          "PERSON": [
            "Sudeep",
            "Pharma Raises Rs",
            "Sudeep Pharma Pvt"
          ],
          "ORGANIZATION": [
            "IPO"
          ],
          "GPE": []
        },
        "financial_keywords": {
          "positive": [],
          "negative": [],
          "neutral": [
            "announce"
          ]
        },
        "numbers": [
          "268",
          "268.5",
          "1753"
        ],
        "percentages": [],
        "dates": [],
        "top_words": [
          [
            "sudeep",
            2
          ],
          [
            "pharma",
            2
          ],
          [
            "crore",
            2
          ],
          [
            "anchor",
            2
          ],
          [
            "investor",
            2
          ],
          [
            "ahead",
            2
          ],
          [
            "ipo",
            2
          ],
          [
            "raise",
            1
          ],
          [
            "268",
            1
          ],
          [
            "pvt",
            1
          ]
        ],
        "stats": {
          "num_entities": 4,
          "num_positive_keywords": 0,
          "num_negative_keywords": 0,
          "num_neutral_keywords": 1,
          "num_numbers": 3,
          "num_percentages": 0,
          "num_dates": 0
        }
      },
      "tokens": {
        "original": [
          "sudeep",
          "pharma",
          "raises",
          "rs",
          "268",
          "crore",
          "from",
          "anchor",
          "investors",
          "ahead",
          "of",
          "ipo",
          ".",
          "sudeep",
          "pharma",
          "pvt",
          ".",
          "ltd.",
          "announced",
          "that",
          "it",
          "garnered",
          "rs",
          "268.5",
          "crore",
          "from",
          "anchor",
          "investors",
          "on",
          "thursday",
          ",",
          "ahead",
          "of",
          "its",
          "initial",
          "public",
          "offer",
          "ipo",
          ",",
          "which",
          "begins",
          "on",
          "friday",
          ",",
          "as",
          "per",
          "an",
          "exchange",
          "filing",
          "on",
          "bse",
          ".",
          "1753",
          "chars"
        ],
        "filtered": [
          "sudeep",
          "pharma",
          "raises",
          "rs",
          "268",
          "crore",
          "anchor",
          "investors",
          "ahead",
          "ipo",
          ".",
          "sudeep",
          "pharma",
          "pvt",
          ".",
          "ltd.",
          "announced",
          "garnered",
          "rs",
          "268.5",
          "crore",
          "anchor",
          "investors",
          "thursday",
          ",",
          "ahead",
          "initial",
          "public",
          "offer",
          "ipo",
          ",",
          "begins",
          "friday",
          ",",
          "per",
          "exchange",
          "filing",
          "bse",
          ".",
          "1753",
          "chars"
        ],
        "lemmatized": [
          "sudeep",
          "pharma",
          "raise",
          "rs",
          "268",
          "crore",
          "anchor",
          "investor",
          "ahead",
          "ipo",
          ".",
          "sudeep",
          "pharma",
          "pvt",
          ".",
          "ltd.",
          "announce",
          "garnered",
          "r",
          "268.5",
          "crore",
          "anchor",
          "investor",
          "thursday",
          ",",
          "ahead",
          "initial",
          "public",
          "offer",
          "ipo",
          ",",
          "begin",
          "friday",
          ",",
          "per",
          "exchange",
          "filing",
          "bse",
          ".",
          "1753",
          "char"
        ]
      }
    },
    {
      "article_id": "655e5a0444554e22",
      "title": "Elon Musk Back At White House For Trumps Dinner With Saudi Crown Prince In First Visit Since Public Feud - Apple NASDAQAAPL , Amazon.com NASDAQAMZN",
      "body": "Tesla Inc. NASDAQTSLA CEO Elon Musk made a high-profile return to the White House on Tuesday, joining a dinner hosted by President Donald Trump in honor of Saudi Crown Prince Mohammed bin Salman, marking his first public appearance there since a widely publicized fallout with Trump earlier ...",
      "source": "Benzinga",
      "timestamp": "2025-11-22T00:25:43.428573",
      "url": "https://www.benzinga.com/news/events/25/11/48942842/elon-musk-back-at-white-house-for-trumps-dinner-with-saudi-crown-prince-in-first-visit-since-public-f",
      "raw_text": "Elon Musk Back At White House For Trumps Dinner With Saudi Crown Prince In First Visit Since Public Feud - Apple NASDAQAAPL , Amazon.com NASDAQAMZN. Tesla Inc. NASDAQTSLA CEO Elon Musk made a high-profile return to the White House on Tuesday, joining a dinner hosted by President Donald Trump in honor of Saudi Crown Prince Mohammed bin Salman, marking his first public appearance there since a widely publicized fallout with Trump earlier ...",
      "tickers_mentioned": "CCI,FSLR,TSLA,PSA,AMZN,AAPL",
      "sentiment": "neutral",
      "ticker_contexts": {
        "CCI": [],
        "FSLR": [],
        "TSLA": [],
        "PSA": [],
        "AMZN": [
          "Visit Since Public Feud - Apple ( NASDAQ:AAPL ) , **Amazon.com** ( NASDAQ:AMZN ) . Tesla Inc. ( NASDAQ:TSLA ) CEO"
        ],
        "AAPL": []
      },
      "features": {
        "entities": {
          "PERSON": [
            "Elon",
            "Musk Back",
            "Public Feud",
            "Tesla Inc.",
            "Donald Trump",
            "Mohammed",
            "Salman",
            "Trump"
          ],
          "ORGANIZATION": [
            "For Trump",
            "NASDAQ",
            "Amazon.com",
            "CEO Elon Musk"
          ],
          "GPE": [
            "Saudi",
            "Apple"
          ]
        },
        "financial_keywords": {
          "positive": [
            "high"
          ],
          "negative": [
            "fall"
          ],
          "neutral": []
        },
        "numbers": [],
        "percentages": [],
        "dates": [],
        "top_words": [
          [
            "trump",
            3
          ],
          [
            "elon",
            2
          ],
          [
            "musk",
            2
          ],
          [
            "white",
            2
          ],
          [
            "house",
            2
          ],
          [
            "dinner",
            2
          ],
          [
            "saudi",
            2
          ],
          [
            "crown",
            2
          ],
          [
            "prince",
            2
          ],
          [
            "first",
            2
          ]
        ],
        "stats": {
          "num_entities": 14,
          "num_positive_keywords": 1,
          "num_negative_keywords": 1,
          "num_neutral_keywords": 0,
          "num_numbers": 0,
          "num_percentages": 0,
          "num_dates": 0
        }
      },
      "tokens": {
        "original": [
          "elon",
          "musk",
          "back",
          "at",
          "white",
          "house",
          "for",
          "trumps",
          "dinner",
          "with",
          "saudi",
          "crown",
          "prince",
          "in",
          "first",
          "visit",
          "since",
          "public",
          "feud",
          "-",
          "apple",
          "nasdaqaapl",
          ",",
          "amazon.com",
          "nasdaqamzn",
          ".",
          "tesla",
          "inc.",
          "nasdaqtsla",
          "ceo",
          "elon",
          "musk",
          "made",
          "a",
          "high-profile",
          "return",
          "to",
          "the",
          "white",
          "house",
          "on",
          "tuesday",
          ",",
          "joining",
          "a",
          "dinner",
          "hosted",
          "by",
          "president",
          "donald",
          "trump",
          "in",
          "honor",
          "of",
          "saudi",
          "crown",
          "prince",
          "mohammed",
          "bin",
          "salman",
          ",",
          "marking",
          "his",
          "first",
          "public",
          "appearance",
          "there",
          "since",
          "a",
          "widely",
          "publicized",
          "fallout",
          "with",
          "trump",
          "earlier",
          "..."
        ],
        "filtered": [
          "elon",
          "musk",
          "back",
          "white",
          "house",
          "trumps",
          "dinner",
          "saudi",
          "crown",
          "prince",
          "first",
          "visit",
          "since",
          "public",
          "feud",
          "-",
          "apple",
          "nasdaqaapl",
          ",",
          "amazon.com",
          "nasdaqamzn",
          ".",
          "tesla",
          "inc.",
          "nasdaqtsla",
          "ceo",
          "elon",
          "musk",
          "made",
          "high-profile",
          "return",
          "white",
          "house",
          "tuesday",
          ",",
          "joining",
          "dinner",
          "hosted",
          "president",
          "donald",
          "trump",
          "honor",
          "saudi",
          "crown",
          "prince",
          "mohammed",
          "bin",
          "salman",
          ",",
          "marking",
          "first",
          "public",
          "appearance",
          "since",
          "widely",
          "publicized",
          "fallout",
          "trump",
          "earlier",
          "..."
        ],
        "lemmatized": [
          "elon",
          "musk",
          "back",
          "white",
          "house",
          "trump",
          "dinner",
          "saudi",
          "crown",
          "prince",
          "first",
          "visit",
          "since",
          "public",
          "feud",
          "-",
          "apple",
          "nasdaqaapl",
          ",",
          "amazon.com",
          "nasdaqamzn",
          ".",
          "tesla",
          "inc.",
          "nasdaqtsla",
          "ceo",
          "elon",
          "musk",
          "make",
          "high-profile",
          "return",
          "white",
          "house",
          "tuesday",
          ",",
          "join",
          "dinner",
          "host",
          "president",
          "donald",
          "trump",
          "honor",
          "saudi",
          "crown",
          "prince",
          "mohammed",
          "bin",
          "salman",
          ",",
          "mark",
          "first",
          "public",
          "appearance",
          "since",
          "widely",
          "publicize",
          "fallout",
          "trump",
          "earlier",
          "..."
        ]
      }
    },
    {
      "article_id": "e4693e6cb66065aa",
      "title": "Nvidias earnings attest to its leadership in the AI race. By the numbers",
      "body": "Nvidia reported more eye-catching numbers for its fiscal third quarter Wednesday, with net income jumping 65 percent and revenue increasing 62 percent from a year earlier. Last month, Nvidia became the first public company to reach a market capitalization of $5 trillion. The ravenous appetite for the Silicon Valley companys chips is the main reason that the companys stock price has increased so rapidly since early 2023.",
      "source": "Yahoo",
      "timestamp": "2025-11-22T00:25:43.949571",
      "url": "https://finnhub.io/api/news?id=97573ee06b98aedfe7d3fe4b45a41f3ca06c1c20d3ad6153ccdd455f6af89b23",
      "raw_text": "Nvidias earnings attest to its leadership in the AI race. By the numbers. Nvidia reported more eye-catching numbers for its fiscal third quarter Wednesday, with net income jumping 65 percent and revenue increasing 62 percent from a year earlier. Last month, Nvidia became the first public company to reach a market capitalization of $5 trillion. The ravenous appetite for the Silicon Valley companys chips is the main reason that the companys stock price has increased so rapidly since early 2023.",
      "tickers_mentioned": "PSA,NVDA,FSLR",
      "sentiment": "positive",
      "ticker_contexts": {
        "PSA": [],
        "NVDA": [
          "**Nvidia's** earnings attest to its leadership in the AI race. By",
          "to its leadership in the AI race. By the numbers. **Nvidia** reported more eye-catching numbers for its fiscal third quarter Wednesday,",
          "and revenue increasing 62% from a year earlier. Last month, **Nvidia** became the first public company to reach a market capitalization"
        ],
        "FSLR": []
      },
      "features": {
        "entities": {
          "PERSON": [
            "Nvidia"
          ],
          "ORGANIZATION": [
            "AI",
            "Silicon Valley"
          ],
          "GPE": [
            "Nvidia"
          ]
        },
        "financial_keywords": {
          "positive": [
            "jump"
          ],
          "negative": [],
          "neutral": [
            "report",
            "quarter",
            "earnings",
            "revenue"
          ]
        },
        "numbers": [
          "65",
          "62",
          "5",
          "2023"
        ],
        "percentages": [],
        "dates": [],
        "top_words": [
          [
            "company",
            3
          ],
          [
            "number",
            2
          ],
          [
            "nvidia",
            2
          ],
          [
            "percent",
            2
          ],
          [
            "increase",
            2
          ],
          [
            "nvidias",
            1
          ],
          [
            "earnings",
            1
          ],
          [
            "attest",
            1
          ],
          [
            "leadership",
            1
          ],
          [
            "race",
            1
          ]
        ],
        "stats": {
          "num_entities": 4,
          "num_positive_keywords": 1,
          "num_negative_keywords": 0,
          "num_neutral_keywords": 4,
          "num_numbers": 4,
          "num_percentages": 0,
          "num_dates": 0
        }
      },
      "tokens": {
        "original": [
          "nvidias",
          "earnings",
          "attest",
          "to",
          "its",
          "leadership",
          "in",
          "the",
          "ai",
          "race",
          ".",
          "by",
          "the",
          "numbers",
          ".",
          "nvidia",
          "reported",
          "more",
          "eye-catching",
          "numbers",
          "for",
          "its",
          "fiscal",
          "third",
          "quarter",
          "wednesday",
          ",",
          "with",
          "net",
          "income",
          "jumping",
          "65",
          "percent",
          "and",
          "revenue",
          "increasing",
          "62",
          "percent",
          "from",
          "a",
          "year",
          "earlier",
          ".",
          "last",
          "month",
          ",",
          "nvidia",
          "became",
          "the",
          "first",
          "public",
          "company",
          "to",
          "reach",
          "a",
          "market",
          "capitalization",
          "of",
          "$",
          "5",
          "trillion",
          ".",
          "the",
          "ravenous",
          "appetite",
          "for",
          "the",
          "silicon",
          "valley",
          "companys",
          "chips",
          "is",
          "the",
          "main",
          "reason",
          "that",
          "the",
          "companys",
          "stock",
          "price",
          "has",
          "increased",
          "so",
          "rapidly",
          "since",
          "early",
          "2023",
          "."
        ],
        "filtered": [
          "nvidias",
          "earnings",
          "attest",
          "leadership",
          "ai",
          "race",
          ".",
          "numbers",
          ".",
          "nvidia",
          "reported",
          "more",
          "eye-catching",
          "numbers",
          "fiscal",
          "third",
          "quarter",
          "wednesday",
          ",",
          "net",
          "income",
          "jumping",
          "65",
          "percent",
          "revenue",
          "increasing",
          "62",
          "percent",
          "year",
          "earlier",
          ".",
          "last",
          "month",
          ",",
          "nvidia",
          "became",
          "first",
          "public",
          "company",
          "reach",
          "market",
          "capitalization",
          "$",
          "5",
          "trillion",
          ".",
          "ravenous",
          "appetite",
          "silicon",
          "valley",
          "companys",
          "chips",
          "main",
          "reason",
          "companys",
          "stock",
          "price",
          "increased",
          "rapidly",
          "since",
          "early",
          "2023",
          "."
        ],
        "lemmatized": [
          "nvidias",
          "earnings",
          "attest",
          "leadership",
          "ai",
          "race",
          ".",
          "number",
          ".",
          "nvidia",
          "report",
          "more",
          "eye-catching",
          "number",
          "fiscal",
          "third",
          "quarter",
          "wednesday",
          ",",
          "net",
          "income",
          "jumping",
          "65",
          "percent",
          "revenue",
          "increase",
          "62",
          "percent",
          "year",
          "earlier",
          ".",
          "last",
          "month",
          ",",
          "nvidia",
          "become",
          "first",
          "public",
          "company",
          "reach",
          "market",
          "capitalization",
          "$",
          "5",
          "trillion",
          ".",
          "ravenous",
          "appetite",
          "silicon",
          "valley",
          "company",
          "chip",
          "main",
          "reason",
          "company",
          "stock",
          "price",
          "increase",
          "rapidly",
          "since",
          "early",
          "2023",
          "."
        ]
      }
    },
    {
      "article_id": "7f2c86badfacf6eb",
      "title": "Tesla NASDAQ TSLA Stock Price Prediction and Forecast 2025-2030 Nov 20",
      "body": "Tesla Inc.s NASDAQ TSLA share price is fractionally higher than a week ago. The company has rolled out its Robotaxi app to the public in the United States and Canada, its next-generation AI5 chip 141 chars",
      "source": "Biztoc.com",
      "timestamp": "2025-11-22T00:25:45.637961",
      "url": "https://biztoc.com/x/dbc00c15b1088401",
      "raw_text": "Tesla NASDAQ TSLA Stock Price Prediction and Forecast 2025-2030 Nov 20. Tesla Inc.s NASDAQ TSLA share price is fractionally higher than a week ago. The company has rolled out its Robotaxi app to the public in the United States and Canada, its next-generation AI5 chip 141 chars",
      "tickers_mentioned": "URI,PSA,TSLA",
      "sentiment": "positive",
      "ticker_contexts": {
        "URI": [],
        "PSA": [],
        "TSLA": []
      },
      "features": {
        "entities": {
          "PERSON": [
            "Stock Price",
            "Tesla"
          ],
          "ORGANIZATION": [
            "NASDAQ",
            "AI5"
          ],
          "GPE": [
            "Tesla",
            "United States",
            "Canada"
          ]
        },
        "financial_keywords": {
          "positive": [
            "high"
          ],
          "negative": [],
          "neutral": [
            "state",
            "forecast"
          ]
        },
        "numbers": [
          "2025",
          "2030",
          "20",
          "141"
        ],
        "percentages": [],
        "dates": [],
        "top_words": [
          [
            "tesla",
            2
          ],
          [
            "nasdaq",
            2
          ],
          [
            "tsla",
            2
          ],
          [
            "price",
            2
          ],
          [
            "stock",
            1
          ],
          [
            "prediction",
            1
          ],
          [
            "forecast",
            1
          ],
          [
            "2025-2030",
            1
          ],
          [
            "nov",
            1
          ],
          [
            "20.",
            1
          ]
        ],
        "stats": {
          "num_entities": 7,
          "num_positive_keywords": 1,
          "num_negative_keywords": 0,
          "num_neutral_keywords": 2,
          "num_numbers": 4,
          "num_percentages": 0,
          "num_dates": 0
        }
      },
      "tokens": {
        "original": [
          "tesla",
          "nasdaq",
          "tsla",
          "stock",
          "price",
          "prediction",
          "and",
          "forecast",
          "2025-2030",
          "nov",
          "20.",
          "tesla",
          "inc.s",
          "nasdaq",
          "tsla",
          "share",
          "price",
          "is",
          "fractionally",
          "higher",
          "than",
          "a",
          "week",
          "ago",
          ".",
          "the",
          "company",
          "has",
          "rolled",
          "out",
          "its",
          "robotaxi",
          "app",
          "to",
          "the",
          "public",
          "in",
          "the",
          "united",
          "states",
          "and",
          "canada",
          ",",
          "its",
          "next-generation",
          "ai5",
          "chip",
          "141",
          "chars"
        ],
        "filtered": [
          "tesla",
          "nasdaq",
          "tsla",
          "stock",
          "price",
          "prediction",
          "forecast",
          "2025-2030",
          "nov",
          "20.",
          "tesla",
          "inc.s",
          "nasdaq",
          "tsla",
          "share",
          "price",
          "fractionally",
          "higher",
          "week",
          "ago",
          ".",
          "company",
          "rolled",
          "robotaxi",
          "app",
          "public",
          "united",
          "states",
          "canada",
          ",",
          "next-generation",
          "ai5",
          "chip",
          "141",
          "chars"
        ],
        "lemmatized": [
          "tesla",
          "nasdaq",
          "tsla",
          "stock",
          "price",
          "prediction",
          "forecast",
          "2025-2030",
          "nov",
          "20.",
          "tesla",
          "inc.s",
          "nasdaq",
          "tsla",
          "share",
          "price",
          "fractionally",
          "high",
          "week",
          "ago",
          ".",
          "company",
          "roll",
          "robotaxi",
          "app",
          "public",
          "united",
          "state",
          "canada",
          ",",
          "next-generation",
          "ai5",
          "chip",
          "141",
          "char"
        ]
      }
    },
    {
      "article_id": "492699e870b1566b",
      "title": "Blockfusion, Owner-Operator of a Strategically Located Clean Energy-Powered Data Center, to Go Public via Business Combination with Blue Acquisition Corp.",
      "body": "Blockfusion USA, Inc. Blockfusion or the Company, a data center infrastructure company, and Blue Acquisition Corp. Nasdaq BACC Blue Acquisition, a publicly traded special purpose acquisition company, today announced that the companies have entered into a definitive business combination agreement the Business Combination Agreement, dated as of November 19, 2025. Upon consummation, if any, of the transaction the Closing, Blockfusions business will be operated by the surviving",
      "source": "Yahoo",
      "timestamp": "2025-11-22T00:25:47.537399",
      "url": "https://finnhub.io/api/news?id=a0ef8d04fc98fcfa1361a9c74fa470fd6845c0faea2a1351dc2d92b70c2c0081",
      "raw_text": "Blockfusion, Owner-Operator of a Strategically Located Clean Energy-Powered Data Center, to Go Public via Business Combination with Blue Acquisition Corp.. Blockfusion USA, Inc. Blockfusion or the Company, a data center infrastructure company, and Blue Acquisition Corp. Nasdaq BACC Blue Acquisition, a publicly traded special purpose acquisition company, today announced that the companies have entered into a definitive business combination agreement the Business Combination Agreement, dated as of November 19, 2025. Upon consummation, if any, of the transaction the Closing, Blockfusions business will be operated by the surviving",
      "tickers_mentioned": "PSA",
      "sentiment": "neutral",
      "ticker_contexts": {
        "PSA": []
      },
      "features": {
        "entities": {
          "PERSON": [
            "Clean",
            "Public",
            "Blue Acquisition Corp",
            "Blue Acquisition",
            "Nasdaq",
            "Blockfusion"
          ],
          "ORGANIZATION": [
            "Business Combination"
          ],
          "GPE": [
            "Blockfusion",
            "Inc."
          ]
        },
        "financial_keywords": {
          "positive": [],
          "negative": [],
          "neutral": [
            "announce"
          ]
        },
        "numbers": [
          "19",
          "2025"
        ],
        "percentages": [],
        "dates": [
          "November 19, 2025"
        ],
        "top_words": [
          [
            "business",
            4
          ],
          [
            "acquisition",
            4
          ],
          [
            "company",
            4
          ],
          [
            "blockfusion",
            3
          ],
          [
            "combination",
            3
          ],
          [
            "blue",
            3
          ],
          [
            "data",
            2
          ],
          [
            "center",
            2
          ],
          [
            "agreement",
            2
          ],
          [
            "owner-operator",
            1
          ]
        ],
        "stats": {
          "num_entities": 9,
          "num_positive_keywords": 0,
          "num_negative_keywords": 0,
          "num_neutral_keywords": 1,
          "num_numbers": 2,
          "num_percentages": 0,
          "num_dates": 1
        }
      },
      "tokens": {
        "original": [
          "blockfusion",
          ",",
          "owner-operator",
          "of",
          "a",
          "strategically",
          "located",
          "clean",
          "energy-powered",
          "data",
          "center",
          ",",
          "to",
          "go",
          "public",
          "via",
          "business",
          "combination",
          "with",
          "blue",
          "acquisition",
          "corp",
          "..",
          "blockfusion",
          "usa",
          ",",
          "inc.",
          "blockfusion",
          "or",
          "the",
          "company",
          ",",
          "a",
          "data",
          "center",
          "infrastructure",
          "company",
          ",",
          "and",
          "blue",
          "acquisition",
          "corp.",
          "nasdaq",
          "bacc",
          "blue",
          "acquisition",
          ",",
          "a",
          "publicly",
          "traded",
          "special",
          "purpose",
          "acquisition",
          "company",
          ",",
          "today",
          "announced",
          "that",
          "the",
          "companies",
          "have",
          "entered",
          "into",
          "a",
          "definitive",
          "business",
          "combination",
          "agreement",
          "the",
          "business",
          "combination",
          "agreement",
          ",",
          "dated",
          "as",
          "of",
          "november",
          "19",
          ",",
          "2025.",
          "upon",
          "consummation",
          ",",
          "if",
          "any",
          ",",
          "of",
          "the",
          "transaction",
          "the",
          "closing",
          ",",
          "blockfusions",
          "business",
          "will",
          "be",
          "operated",
          "by",
          "the",
          "surviving"
        ],
        "filtered": [
          "blockfusion",
          ",",
          "owner-operator",
          "strategically",
          "located",
          "clean",
          "energy-powered",
          "data",
          "center",
          ",",
          "go",
          "public",
          "via",
          "business",
          "combination",
          "blue",
          "acquisition",
          "corp",
          "..",
          "blockfusion",
          "usa",
          ",",
          "inc.",
          "blockfusion",
          "company",
          ",",
          "data",
          "center",
          "infrastructure",
          "company",
          ",",
          "blue",
          "acquisition",
          "corp.",
          "nasdaq",
          "bacc",
          "blue",
          "acquisition",
          ",",
          "publicly",
          "traded",
          "special",
          "purpose",
          "acquisition",
          "company",
          ",",
          "today",
          "announced",
          "companies",
          "entered",
          "definitive",
          "business",
          "combination",
          "agreement",
          "business",
          "combination",
          "agreement",
          ",",
          "dated",
          "november",
          "19",
          ",",
          "2025.",
          "upon",
          "consummation",
          ",",
          ",",
          "transaction",
          "closing",
          ",",
          "blockfusions",
          "business",
          "operated",
          "surviving"
        ],
        "lemmatized": [
          "blockfusion",
          ",",
          "owner-operator",
          "strategically",
          "locate",
          "clean",
          "energy-powered",
          "data",
          "center",
          ",",
          "go",
          "public",
          "via",
          "business",
          "combination",
          "blue",
          "acquisition",
          "corp",
          "..",
          "blockfusion",
          "usa",
          ",",
          "inc.",
          "blockfusion",
          "company",
          ",",
          "data",
          "center",
          "infrastructure",
          "company",
          ",",
          "blue",
          "acquisition",
          "corp.",
          "nasdaq",
          "bacc",
          "blue",
          "acquisition",
          ",",
          "publicly",
          "trade",
          "special",
          "purpose",
          "acquisition",
          "company",
          ",",
          "today",
          "announce",
          "company",
          "enter",
          "definitive",
          "business",
          "combination",
          "agreement",
          "business",
          "combination",
          "agreement",
          ",",
          "date",
          "november",
          "19",
          ",",
          "2025.",
          "upon",
          "consummation",
          ",",
          ",",
          "transaction",
          "closing",
          ",",
          "blockfusions",
          "business",
          "operate",
          "survive"
        ]
      }
    },
    {
      "article_id": "08632062af880648",
      "title": "IDEMIA Public Security Expands Collaboration with Microsoft as a Launch Partner of Microsoft Entra Verified ID",
      "body": "IDEMIA Public Security, the leading provider of secure and trusted biometric-based solutions, has been selected as a launch partner of Microsoft Entra Verified ID after a successful pilot, strengthening their partnership with Microsoft to authenticate individuals with proof of identity, and issuance of credentials that enable a host of use cases across Microsofts ecosystem of partners and customers enabled through IDEMIAs identity and verification technology.",
      "source": "Yahoo",
      "timestamp": "2025-11-22T00:25:49.529896",
      "url": "https://finnhub.io/api/news?id=73d4e7d7b90913ed66a48dac415f62a33f48f5f45bcef34c70cc1ecccdefa406",
      "raw_text": "IDEMIA Public Security Expands Collaboration with Microsoft as a Launch Partner of Microsoft Entra Verified ID. IDEMIA Public Security, the leading provider of secure and trusted biometric-based solutions, has been selected as a launch partner of Microsoft Entra Verified ID after a successful pilot, strengthening their partnership with Microsoft to authenticate individuals with proof of identity, and issuance of credentials that enable a host of use cases across Microsofts ecosystem of partners and customers enabled through IDEMIAs identity and verification technology.",
      "tickers_mentioned": "PSA,HST,MSFT",
      "sentiment": "neutral",
      "ticker_contexts": {
        "PSA": [],
        "HST": [],
        "MSFT": [
          "IDEMIA Public Security Expands Collaboration with **Microsoft** as a Launch Partner of Microsoft Entra Verified ID. IDEMIA",
          "Security Expands Collaboration with Microsoft as a Launch Partner of **Microsoft** Entra Verified ID. IDEMIA Public Security, the leading provider of",
          "biometric-based solutions, has been selected as a launch partner of **Microsoft** Entra Verified ID after a successful pilot, strengthening their partnership",
          "Verified ID after a successful pilot, strengthening their partnership with **Microsoft** to authenticate individuals with proof of identity, and issuance of",
          "of credentials that enable a host of use cases across **Microsoft's** ecosystem of partners and customers enabled through IDEMIA's identity and"
        ]
      },
      "features": {
        "entities": {
          "PERSON": [
            "Public Security Expands Collaboration",
            "Microsoft"
          ],
          "ORGANIZATION": [
            "IDEMIA",
            "Launch Partner",
            "Microsoft Entra Verified",
            "IDEMIA Public"
          ],
          "GPE": []
        },
        "financial_keywords": {
          "positive": [],
          "negative": [],
          "neutral": []
        },
        "numbers": [],
        "percentages": [],
        "dates": [],
        "top_words": [
          [
            "microsoft",
            4
          ],
          [
            "partner",
            3
          ],
          [
            "idemia",
            2
          ],
          [
            "public",
            2
          ],
          [
            "security",
            2
          ],
          [
            "launch",
            2
          ],
          [
            "entra",
            2
          ],
          [
            "verify",
            2
          ],
          [
            "identity",
            2
          ],
          [
            "enable",
            2
          ]
        ],
        "stats": {
          "num_entities": 6,
          "num_positive_keywords": 0,
          "num_negative_keywords": 0,
          "num_neutral_keywords": 0,
          "num_numbers": 0,
          "num_percentages": 0,
          "num_dates": 0
        }
      },
      "tokens": {
        "original": [
          "idemia",
          "public",
          "security",
          "expands",
          "collaboration",
          "with",
          "microsoft",
          "as",
          "a",
          "launch",
          "partner",
          "of",
          "microsoft",
          "entra",
          "verified",
          "id",
          ".",
          "idemia",
          "public",
          "security",
          ",",
          "the",
          "leading",
          "provider",
          "of",
          "secure",
          "and",
          "trusted",
          "biometric-based",
          "solutions",
          ",",
          "has",
          "been",
          "selected",
          "as",
          "a",
          "launch",
          "partner",
          "of",
          "microsoft",
          "entra",
          "verified",
          "id",
          "after",
          "a",
          "successful",
          "pilot",
          ",",
          "strengthening",
          "their",
          "partnership",
          "with",
          "microsoft",
          "to",
          "authenticate",
          "individuals",
          "with",
          "proof",
          "of",
          "identity",
          ",",
          "and",
          "issuance",
          "of",
          "credentials",
          "that",
          "enable",
          "a",
          "host",
          "of",
          "use",
          "cases",
          "across",
          "microsofts",
          "ecosystem",
          "of",
          "partners",
          "and",
          "customers",
          "enabled",
          "through",
          "idemias",
          "identity",
          "and",
          "verification",
          "technology",
          "."
        ],
        "filtered": [
          "idemia",
          "public",
          "security",
          "expands",
          "collaboration",
          "microsoft",
          "launch",
          "partner",
          "microsoft",
          "entra",
          "verified",
          "id",
          ".",
          "idemia",
          "public",
          "security",
          ",",
          "leading",
          "provider",
          "secure",
          "trusted",
          "biometric-based",
          "solutions",
          ",",
          "selected",
          "launch",
          "partner",
          "microsoft",
          "entra",
          "verified",
          "id",
          "successful",
          "pilot",
          ",",
          "strengthening",
          "partnership",
          "microsoft",
          "authenticate",
          "individuals",
          "proof",
          "identity",
          ",",
          "issuance",
          "credentials",
          "enable",
          "host",
          "use",
          "cases",
          "across",
          "microsofts",
          "ecosystem",
          "partners",
          "customers",
          "enabled",
          "idemias",
          "identity",
          "verification",
          "technology",
          "."
        ],
        "lemmatized": [
          "idemia",
          "public",
          "security",
          "expand",
          "collaboration",
          "microsoft",
          "launch",
          "partner",
          "microsoft",
          "entra",
          "verify",
          "id",
          ".",
          "idemia",
          "public",
          "security",
          ",",
          "lead",
          "provider",
          "secure",
          "trust",
          "biometric-based",
          "solution",
          ",",
          "select",
          "launch",
          "partner",
          "microsoft",
          "entra",
          "verify",
          "id",
          "successful",
          "pilot",
          ",",
          "strengthen",
          "partnership",
          "microsoft",
          "authenticate",
          "individual",
          "proof",
          "identity",
          ",",
          "issuance",
          "credential",
          "enable",
          "host",
          "use",
          "case",
          "across",
          "microsofts",
          "ecosystem",
          "partner",
          "customer",
          "enable",
          "idemias",
          "identity",
          "verification",
          "technology",
          "."
        ]
      }
    },
    {
      "article_id": "e4693e6cb66065aa",
      "title": "Nvidias earnings attest to its leadership in the AI race. By the numbers",
      "body": "Nvidia reported more eye-catching numbers for its fiscal third quarter Wednesday, with net income jumping 65 percent and revenue increasing 62 percent from a year earlier. Last month, Nvidia became the first public company to reach a market capitalization of $5 trillion. The ravenous appetite for the Silicon Valley companys chips is the main reason that the companys stock price has increased so rapidly since early 2023.",
      "source": "Yahoo",
      "timestamp": "2025-11-22T00:25:50.119077",
      "url": "https://finnhub.io/api/news?id=97573ee06b98aedfe7d3fe4b45a41f3ca06c1c20d3ad6153ccdd455f6af89b23",
      "raw_text": "Nvidias earnings attest to its leadership in the AI race. By the numbers. Nvidia reported more eye-catching numbers for its fiscal third quarter Wednesday, with net income jumping 65 percent and revenue increasing 62 percent from a year earlier. Last month, Nvidia became the first public company to reach a market capitalization of $5 trillion. The ravenous appetite for the Silicon Valley companys chips is the main reason that the companys stock price has increased so rapidly since early 2023.",
      "tickers_mentioned": "PSA,NVDA,FSLR",
      "sentiment": "positive",
      "ticker_contexts": {
        "PSA": [],
        "NVDA": [
          "**Nvidia's** earnings attest to its leadership in the AI race. By",
          "to its leadership in the AI race. By the numbers. **Nvidia** reported more eye-catching numbers for its fiscal third quarter Wednesday,",
          "and revenue increasing 62% from a year earlier. Last month, **Nvidia** became the first public company to reach a market capitalization"
        ],
        "FSLR": []
      },
      "features": {
        "entities": {
          "PERSON": [
            "Nvidia"
          ],
          "ORGANIZATION": [
            "AI",
            "Silicon Valley"
          ],
          "GPE": [
            "Nvidia"
          ]
        },
        "financial_keywords": {
          "positive": [
            "jump"
          ],
          "negative": [],
          "neutral": [
            "report",
            "quarter",
            "earnings",
            "revenue"
          ]
        },
        "numbers": [
          "65",
          "62",
          "5",
          "2023"
        ],
        "percentages": [],
        "dates": [],
        "top_words": [
          [
            "company",
            3
          ],
          [
            "number",
            2
          ],
          [
            "nvidia",
            2
          ],
          [
            "percent",
            2
          ],
          [
            "increase",
            2
          ],
          [
            "nvidias",
            1
          ],
          [
            "earnings",
            1
          ],
          [
            "attest",
            1
          ],
          [
            "leadership",
            1
          ],
          [
            "race",
            1
          ]
        ],
        "stats": {
          "num_entities": 4,
          "num_positive_keywords": 1,
          "num_negative_keywords": 0,
          "num_neutral_keywords": 4,
          "num_numbers": 4,
          "num_percentages": 0,
          "num_dates": 0
        }
      },
      "tokens": {
        "original": [
          "nvidias",
          "earnings",
          "attest",
          "to",
          "its",
          "leadership",
          "in",
          "the",
          "ai",
          "race",
          ".",
          "by",
          "the",
          "numbers",
          ".",
          "nvidia",
          "reported",
          "more",
          "eye-catching",
          "numbers",
          "for",
          "its",
          "fiscal",
          "third",
          "quarter",
          "wednesday",
          ",",
          "with",
          "net",
          "income",
          "jumping",
          "65",
          "percent",
          "and",
          "revenue",
          "increasing",
          "62",
          "percent",
          "from",
          "a",
          "year",
          "earlier",
          ".",
          "last",
          "month",
          ",",
          "nvidia",
          "became",
          "the",
          "first",
          "public",
          "company",
          "to",
          "reach",
          "a",
          "market",
          "capitalization",
          "of",
          "$",
          "5",
          "trillion",
          ".",
          "the",
          "ravenous",
          "appetite",
          "for",
          "the",
          "silicon",
          "valley",
          "companys",
          "chips",
          "is",
          "the",
          "main",
          "reason",
          "that",
          "the",
          "companys",
          "stock",
          "price",
          "has",
          "increased",
          "so",
          "rapidly",
          "since",
          "early",
          "2023",
          "."
        ],
        "filtered": [
          "nvidias",
          "earnings",
          "attest",
          "leadership",
          "ai",
          "race",
          ".",
          "numbers",
          ".",
          "nvidia",
          "reported",
          "more",
          "eye-catching",
          "numbers",
          "fiscal",
          "third",
          "quarter",
          "wednesday",
          ",",
          "net",
          "income",
          "jumping",
          "65",
          "percent",
          "revenue",
          "increasing",
          "62",
          "percent",
          "year",
          "earlier",
          ".",
          "last",
          "month",
          ",",
          "nvidia",
          "became",
          "first",
          "public",
          "company",
          "reach",
          "market",
          "capitalization",
          "$",
          "5",
          "trillion",
          ".",
          "ravenous",
          "appetite",
          "silicon",
          "valley",
          "companys",
          "chips",
          "main",
          "reason",
          "companys",
          "stock",
          "price",
          "increased",
          "rapidly",
          "since",
          "early",
          "2023",
          "."
        ],
        "lemmatized": [
          "nvidias",
          "earnings",
          "attest",
          "leadership",
          "ai",
          "race",
          ".",
          "number",
          ".",
          "nvidia",
          "report",
          "more",
          "eye-catching",
          "number",
          "fiscal",
          "third",
          "quarter",
          "wednesday",
          ",",
          "net",
          "income",
          "jumping",
          "65",
          "percent",
          "revenue",
          "increase",
          "62",
          "percent",
          "year",
          "earlier",
          ".",
          "last",
          "month",
          ",",
          "nvidia",
          "become",
          "first",
          "public",
          "company",
          "reach",
          "market",
          "capitalization",
          "$",
          "5",
          "trillion",
          ".",
          "ravenous",
          "appetite",
          "silicon",
          "valley",
          "company",
          "chip",
          "main",
          "reason",
          "company",
          "stock",
          "price",
          "increase",
          "rapidly",
          "since",
          "early",
          "2023",
          "."
        ]
      }
    },
    {
      "article_id": "abf8edfae0419a81",
      "title": "The Most Joyless Tech Revolution Ever AI Is Making Us Rich and Unhappy",
      "body": "Discomfort around artificial intelligence helps explain the disconnect between a solid economy and an anxious public.",
      "source": "Yahoo",
      "timestamp": "2025-11-22T00:25:51.242077",
      "url": "https://finnhub.io/api/news?id=f5804b00808260a4761f3f621e47fd598f3dc7e0b3c5cb03def8e1509dbe422c",
      "raw_text": "The Most Joyless Tech Revolution Ever AI Is Making Us Rich and Unhappy. Discomfort around artificial intelligence helps explain the disconnect between a solid economy and an anxious public.",
      "tickers_mentioned": "PSA,TECH",
      "sentiment": "neutral",
      "ticker_contexts": {
        "PSA": [],
        "TECH": []
      },
      "features": {
        "entities": {
          "PERSON": [
            "Us Rich",
            "Unhappy"
          ],
          "ORGANIZATION": [
            "Most Joyless Tech Revolution"
          ],
          "GPE": []
        },
        "financial_keywords": {
          "positive": [],
          "negative": [],
          "neutral": []
        },
        "numbers": [],
        "percentages": [],
        "dates": [],
        "top_words": [
          [
            "most",
            1
          ],
          [
            "joyless",
            1
          ],
          [
            "tech",
            1
          ],
          [
            "revolution",
            1
          ],
          [
            "ever",
            1
          ],
          [
            "make",
            1
          ],
          [
            "rich",
            1
          ],
          [
            "unhappy",
            1
          ],
          [
            "discomfort",
            1
          ],
          [
            "around",
            1
          ]
        ],
        "stats": {
          "num_entities": 3,
          "num_positive_keywords": 0,
          "num_negative_keywords": 0,
          "num_neutral_keywords": 0,
          "num_numbers": 0,
          "num_percentages": 0,
          "num_dates": 0
        }
      },
      "tokens": {
        "original": [
          "the",
          "most",
          "joyless",
          "tech",
          "revolution",
          "ever",
          "ai",
          "is",
          "making",
          "us",
          "rich",
          "and",
          "unhappy",
          ".",
          "discomfort",
          "around",
          "artificial",
          "intelligence",
          "helps",
          "explain",
          "the",
          "disconnect",
          "between",
          "a",
          "solid",
          "economy",
          "and",
          "an",
          "anxious",
          "public",
          "."
        ],
        "filtered": [
          "most",
          "joyless",
          "tech",
          "revolution",
          "ever",
          "ai",
          "making",
          "us",
          "rich",
          "unhappy",
          ".",
          "discomfort",
          "around",
          "artificial",
          "intelligence",
          "helps",
          "explain",
          "disconnect",
          "solid",
          "economy",
          "anxious",
          "public",
          "."
        ],
        "lemmatized": [
          "most",
          "joyless",
          "tech",
          "revolution",
          "ever",
          "ai",
          "make",
          "u",
          "rich",
          "unhappy",
          ".",
          "discomfort",
          "around",
          "artificial",
          "intelligence",
          "help",
          "explain",
          "disconnect",
          "solid",
          "economy",
          "anxious",
          "public",
          "."
        ]
      }
    },
    {
      "article_id": "8eeda39e8e2b86de",
      "title": "Harvard now owns nearly half a billion dollars worth of Bitcoin, filings show",
      "body": "The Ivy League school invested more than 20 percent of its U.S.-listed public equity holdings in a crypto ETF.",
      "source": "Yahoo",
      "timestamp": "2025-11-22T00:25:51.286607",
      "url": "https://finnhub.io/api/news?id=1a788c994dae930f4f736344df5812d613fa59d29759dc8f3d867825e9642605",
      "raw_text": "Harvard now owns nearly half a billion dollars worth of Bitcoin, filings show. The Ivy League school invested more than 20 percent of its U.S.-listed public equity holdings in a crypto ETF.",
      "tickers_mentioned": "PSA,EQR",
      "sentiment": "neutral",
      "ticker_contexts": {
        "PSA": [],
        "EQR": []
      },
      "features": {
        "entities": {
          "PERSON": [
            "Harvard"
          ],
          "ORGANIZATION": [
            "Ivy League",
            "ETF"
          ],
          "GPE": [
            "Bitcoin"
          ]
        },
        "financial_keywords": {
          "positive": [],
          "negative": [],
          "neutral": [
            "hold"
          ]
        },
        "numbers": [
          "20"
        ],
        "percentages": [],
        "dates": [],
        "top_words": [
          [
            "harvard",
            1
          ],
          [
            "own",
            1
          ],
          [
            "nearly",
            1
          ],
          [
            "half",
            1
          ],
          [
            "billion",
            1
          ],
          [
            "dollar",
            1
          ],
          [
            "worth",
            1
          ],
          [
            "bitcoin",
            1
          ],
          [
            "filing",
            1
          ],
          [
            "show",
            1
          ]
        ],
        "stats": {
          "num_entities": 4,
          "num_positive_keywords": 0,
          "num_negative_keywords": 0,
          "num_neutral_keywords": 1,
          "num_numbers": 1,
          "num_percentages": 0,
          "num_dates": 0
        }
      },
      "tokens": {
        "original": [
          "harvard",
          "now",
          "owns",
          "nearly",
          "half",
          "a",
          "billion",
          "dollars",
          "worth",
          "of",
          "bitcoin",
          ",",
          "filings",
          "show",
          ".",
          "the",
          "ivy",
          "league",
          "school",
          "invested",
          "more",
          "than",
          "20",
          "percent",
          "of",
          "its",
          "u.s.-listed",
          "public",
          "equity",
          "holdings",
          "in",
          "a",
          "crypto",
          "etf",
          "."
        ],
        "filtered": [
          "harvard",
          "owns",
          "nearly",
          "half",
          "billion",
          "dollars",
          "worth",
          "bitcoin",
          ",",
          "filings",
          "show",
          ".",
          "ivy",
          "league",
          "school",
          "invested",
          "more",
          "20",
          "percent",
          "u.s.-listed",
          "public",
          "equity",
          "holdings",
          "crypto",
          "etf",
          "."
        ],
        "lemmatized": [
          "harvard",
          "own",
          "nearly",
          "half",
          "billion",
          "dollar",
          "worth",
          "bitcoin",
          ",",
          "filing",
          "show",
          ".",
          "ivy",
          "league",
          "school",
          "invest",
          "more",
          "20",
          "percent",
          "u.s.-listed",
          "public",
          "equity",
          "holdings",
          "crypto",
          "etf",
          "."
        ]
      }
    },
    {
      "article_id": "0cfaf940790e0829",
      "title": "CoreWeaves Worst-Ever Week Shows AI Traders Are Getting Picky",
      "body": "On one end of the spectrum are companies like CoreWeave Inc., the money-losing provider of computing services that is swimming in debt. Its shares plunged 26 percent last week, marking its worst weekly showing since its debut earlier this year, following on the prior weeks 22 percent decline. The stock had risen more than 400 percent from an April low through June and remains up nearly 90 percent since its March initial public offering.",
      "source": "Yahoo",
      "timestamp": "2025-11-22T00:25:51.479470",
      "url": "https://finnhub.io/api/news?id=cffb04ac823add1f879e5c9e5e6aa1eb81bef4dda4ee138e4a606f05f94473b2",
      "raw_text": "CoreWeaves Worst-Ever Week Shows AI Traders Are Getting Picky. On one end of the spectrum are companies like CoreWeave Inc., the money-losing provider of computing services that is swimming in debt. Its shares plunged 26 percent last week, marking its worst weekly showing since its debut earlier this year, following on the prior weeks 22 percent decline. The stock had risen more than 400 percent from an April low through June and remains up nearly 90 percent since its March initial public offering.",
      "tickers_mentioned": "PSA",
      "sentiment": "negative",
      "ticker_contexts": {
        "PSA": []
      },
      "features": {
        "entities": {
          "PERSON": [
            "Picky"
          ],
          "ORGANIZATION": [
            "CoreWeave",
            "CoreWeave Inc."
          ],
          "GPE": []
        },
        "financial_keywords": {
          "positive": [
            "rise"
          ],
          "negative": [
            "plunge",
            "decline"
          ],
          "neutral": []
        },
        "numbers": [
          "26",
          "22",
          "400",
          "90"
        ],
        "percentages": [],
        "dates": [],
        "top_words": [
          [
            "percent",
            4
          ],
          [
            "week",
            3
          ],
          [
            "since",
            2
          ],
          [
            "coreweaves",
            1
          ],
          [
            "worst-ever",
            1
          ],
          [
            "show",
            1
          ],
          [
            "trader",
            1
          ],
          [
            "get",
            1
          ],
          [
            "picky",
            1
          ],
          [
            "one",
            1
          ]
        ],
        "stats": {
          "num_entities": 3,
          "num_positive_keywords": 1,
          "num_negative_keywords": 2,
          "num_neutral_keywords": 0,
          "num_numbers": 4,
          "num_percentages": 0,
          "num_dates": 0
        }
      },
      "tokens": {
        "original": [
          "coreweaves",
          "worst-ever",
          "week",
          "shows",
          "ai",
          "traders",
          "are",
          "getting",
          "picky",
          ".",
          "on",
          "one",
          "end",
          "of",
          "the",
          "spectrum",
          "are",
          "companies",
          "like",
          "coreweave",
          "inc.",
          ",",
          "the",
          "money-losing",
          "provider",
          "of",
          "computing",
          "services",
          "that",
          "is",
          "swimming",
          "in",
          "debt",
          ".",
          "its",
          "shares",
          "plunged",
          "26",
          "percent",
          "last",
          "week",
          ",",
          "marking",
          "its",
          "worst",
          "weekly",
          "showing",
          "since",
          "its",
          "debut",
          "earlier",
          "this",
          "year",
          ",",
          "following",
          "on",
          "the",
          "prior",
          "weeks",
          "22",
          "percent",
          "decline",
          ".",
          "the",
          "stock",
          "had",
          "risen",
          "more",
          "than",
          "400",
          "percent",
          "from",
          "an",
          "april",
          "low",
          "through",
          "june",
          "and",
          "remains",
          "up",
          "nearly",
          "90",
          "percent",
          "since",
          "its",
          "march",
          "initial",
          "public",
          "offering",
          "."
        ],
        "filtered": [
          "coreweaves",
          "worst-ever",
          "week",
          "shows",
          "ai",
          "traders",
          "getting",
          "picky",
          ".",
          "one",
          "end",
          "spectrum",
          "companies",
          "like",
          "coreweave",
          "inc.",
          ",",
          "money-losing",
          "provider",
          "computing",
          "services",
          "swimming",
          "debt",
          ".",
          "shares",
          "plunged",
          "26",
          "percent",
          "last",
          "week",
          ",",
          "marking",
          "worst",
          "weekly",
          "showing",
          "since",
          "debut",
          "earlier",
          "year",
          ",",
          "following",
          "prior",
          "weeks",
          "22",
          "percent",
          "decline",
          ".",
          "stock",
          "risen",
          "more",
          "400",
          "percent",
          "april",
          "low",
          "june",
          "remains",
          "up",
          "nearly",
          "90",
          "percent",
          "since",
          "march",
          "initial",
          "public",
          "offering",
          "."
        ],
        "lemmatized": [
          "coreweaves",
          "worst-ever",
          "week",
          "show",
          "ai",
          "trader",
          "get",
          "picky",
          ".",
          "one",
          "end",
          "spectrum",
          "company",
          "like",
          "coreweave",
          "inc.",
          ",",
          "money-losing",
          "provider",
          "computing",
          "service",
          "swim",
          "debt",
          ".",
          "shares",
          "plunge",
          "26",
          "percent",
          "last",
          "week",
          ",",
          "mark",
          "bad",
          "weekly",
          "showing",
          "since",
          "debut",
          "earlier",
          "year",
          ",",
          "follow",
          "prior",
          "week",
          "22",
          "percent",
          "decline",
          ".",
          "stock",
          "rise",
          "more",
          "400",
          "percent",
          "april",
          "low",
          "june",
          "remain",
          "up",
          "nearly",
          "90",
          "percent",
          "since",
          "march",
          "initial",
          "public",
          "offering",
          "."
        ]
      }
    },
    {
      "article_id": "5f66408272b87f1a",
      "title": "Heres Why Alphabets Gemini Is Set to Crush ChatGPTs Lead",
      "body": "The launch of ChatGPT by OpenAI in November 2022 marked a turning point in the AI landscape, igniting the broader AI boom. This generative AI tool demonstrated practical applications for everyday users, from content creation to coding assistance, sparking massive public interest and investment. Tech giants poured billions into AI development, while startups flooded the ... Heres Why Alphabets Gemini Is Set to Crush ChatGPTs Lead",
      "source": "Yahoo",
      "timestamp": "2025-11-22T00:25:54.273025",
      "url": "https://finnhub.io/api/news?id=e445a6a622a9e7e9f5647b323d3770f0d3ae6ffb9f7fa4ef86f0b838a3dad055",
      "raw_text": "Heres Why Alphabets Gemini Is Set to Crush ChatGPTs Lead. The launch of ChatGPT by OpenAI in November 2022 marked a turning point in the AI landscape, igniting the broader AI boom. This generative AI tool demonstrated practical applications for everyday users, from content creation to coding assistance, sparking massive public interest and investment. Tech giants poured billions into AI development, while startups flooded the ... Heres Why Alphabets Gemini Is Set to Crush ChatGPTs Lead",
      "tickers_mentioned": "PSA,GOOG,TECH",
      "sentiment": "neutral",
      "ticker_contexts": {
        "PSA": [],
        "GOOG": [],
        "TECH": []
      },
      "features": {
        "entities": {
          "PERSON": [
            "Alphabet",
            "Gemini",
            "Set",
            "Crush ChatGPT"
          ],
          "ORGANIZATION": [
            "ChatGPT",
            "OpenAI",
            "AI"
          ],
          "GPE": []
        },
        "financial_keywords": {
          "positive": [],
          "negative": [],
          "neutral": []
        },
        "numbers": [
          "2022"
        ],
        "percentages": [],
        "dates": [],
        "top_words": [
          [
            "alphabet",
            2
          ],
          [
            "gemini",
            2
          ],
          [
            "set",
            2
          ],
          [
            "crush",
            2
          ],
          [
            "chatgpts",
            2
          ],
          [
            "lead",
            2
          ],
          [
            "here",
            1
          ],
          [
            "launch",
            1
          ],
          [
            "chatgpt",
            1
          ],
          [
            "openai",
            1
          ]
        ],
        "stats": {
          "num_entities": 7,
          "num_positive_keywords": 0,
          "num_negative_keywords": 0,
          "num_neutral_keywords": 0,
          "num_numbers": 1,
          "num_percentages": 0,
          "num_dates": 0
        }
      },
      "tokens": {
        "original": [
          "heres",
          "why",
          "alphabets",
          "gemini",
          "is",
          "set",
          "to",
          "crush",
          "chatgpts",
          "lead",
          ".",
          "the",
          "launch",
          "of",
          "chatgpt",
          "by",
          "openai",
          "in",
          "november",
          "2022",
          "marked",
          "a",
          "turning",
          "point",
          "in",
          "the",
          "ai",
          "landscape",
          ",",
          "igniting",
          "the",
          "broader",
          "ai",
          "boom",
          ".",
          "this",
          "generative",
          "ai",
          "tool",
          "demonstrated",
          "practical",
          "applications",
          "for",
          "everyday",
          "users",
          ",",
          "from",
          "content",
          "creation",
          "to",
          "coding",
          "assistance",
          ",",
          "sparking",
          "massive",
          "public",
          "interest",
          "and",
          "investment",
          ".",
          "tech",
          "giants",
          "poured",
          "billions",
          "into",
          "ai",
          "development",
          ",",
          "while",
          "startups",
          "flooded",
          "the",
          "...",
          "heres",
          "why",
          "alphabets",
          "gemini",
          "is",
          "set",
          "to",
          "crush",
          "chatgpts",
          "lead"
        ],
        "filtered": [
          "heres",
          "alphabets",
          "gemini",
          "set",
          "crush",
          "chatgpts",
          "lead",
          ".",
          "launch",
          "chatgpt",
          "openai",
          "november",
          "2022",
          "marked",
          "turning",
          "point",
          "ai",
          "landscape",
          ",",
          "igniting",
          "broader",
          "ai",
          "boom",
          ".",
          "generative",
          "ai",
          "tool",
          "demonstrated",
          "practical",
          "applications",
          "everyday",
          "users",
          ",",
          "content",
          "creation",
          "coding",
          "assistance",
          ",",
          "sparking",
          "massive",
          "public",
          "interest",
          "investment",
          ".",
          "tech",
          "giants",
          "poured",
          "billions",
          "ai",
          "development",
          ",",
          "startups",
          "flooded",
          "...",
          "heres",
          "alphabets",
          "gemini",
          "set",
          "crush",
          "chatgpts",
          "lead"
        ],
        "lemmatized": [
          "here",
          "alphabet",
          "gemini",
          "set",
          "crush",
          "chatgpts",
          "lead",
          ".",
          "launch",
          "chatgpt",
          "openai",
          "november",
          "2022",
          "mark",
          "turn",
          "point",
          "ai",
          "landscape",
          ",",
          "ignite",
          "broad",
          "ai",
          "boom",
          ".",
          "generative",
          "ai",
          "tool",
          "demonstrate",
          "practical",
          "application",
          "everyday",
          "user",
          ",",
          "content",
          "creation",
          "cod",
          "assistance",
          ",",
          "spark",
          "massive",
          "public",
          "interest",
          "investment",
          ".",
          "tech",
          "giant",
          "pour",
          "billion",
          "ai",
          "development",
          ",",
          "startup",
          "flood",
          "...",
          "heres",
          "alphabet",
          "gemini",
          "set",
          "crush",
          "chatgpts",
          "lead"
        ]
      }
    },
    {
      "article_id": "c4db9ee03ffe139e",
      "title": "India Is in an IPO Frenzy Again. Wait Until It Cools.",
      "body": "Indian internet companies are going public, and investors are jumping in. It may pay to wait until the smoke clears.",
      "source": "Yahoo",
      "timestamp": "2025-11-22T00:25:55.529295",
      "url": "https://finnhub.io/api/news?id=c732b6035f22a038c2e5d9130c3b6804636e2cf99d21bfbe521a04254f82a8ab",
      "raw_text": "India Is in an IPO Frenzy Again. Wait Until It Cools.. Indian internet companies are going public, and investors are jumping in. It may pay to wait until the smoke clears.",
      "tickers_mentioned": "PSA",
      "sentiment": "positive",
      "ticker_contexts": {
        "PSA": []
      },
      "features": {
        "entities": {
          "PERSON": [
            "Is",
            "Wait",
            "Cools"
          ],
          "ORGANIZATION": [
            "IPO Frenzy Again"
          ],
          "GPE": [
            "India"
          ]
        },
        "financial_keywords": {
          "positive": [
            "jump",
            "gain"
          ],
          "negative": [],
          "neutral": []
        },
        "numbers": [],
        "percentages": [],
        "dates": [],
        "top_words": [
          [
            "wait",
            2
          ],
          [
            "india",
            1
          ],
          [
            "ipo",
            1
          ],
          [
            "frenzy",
            1
          ],
          [
            "cool",
            1
          ],
          [
            "indian",
            1
          ],
          [
            "internet",
            1
          ],
          [
            "company",
            1
          ],
          [
            "public",
            1
          ],
          [
            "investor",
            1
          ]
        ],
        "stats": {
          "num_entities": 5,
          "num_positive_keywords": 2,
          "num_negative_keywords": 0,
          "num_neutral_keywords": 0,
          "num_numbers": 0,
          "num_percentages": 0,
          "num_dates": 0
        }
      },
      "tokens": {
        "original": [
          "india",
          "is",
          "in",
          "an",
          "ipo",
          "frenzy",
          "again",
          ".",
          "wait",
          "until",
          "it",
          "cools",
          "..",
          "indian",
          "internet",
          "companies",
          "are",
          "going",
          "public",
          ",",
          "and",
          "investors",
          "are",
          "jumping",
          "in",
          ".",
          "it",
          "may",
          "pay",
          "to",
          "wait",
          "until",
          "the",
          "smoke",
          "clears",
          "."
        ],
        "filtered": [
          "india",
          "ipo",
          "frenzy",
          ".",
          "wait",
          "cools",
          "..",
          "indian",
          "internet",
          "companies",
          "going",
          "public",
          ",",
          "investors",
          "jumping",
          ".",
          "may",
          "pay",
          "wait",
          "smoke",
          "clears",
          "."
        ],
        "lemmatized": [
          "india",
          "ipo",
          "frenzy",
          ".",
          "wait",
          "cool",
          "..",
          "indian",
          "internet",
          "company",
          "go",
          "public",
          ",",
          "investor",
          "jump",
          ".",
          "may",
          "pay",
          "wait",
          "smoke",
          "clear",
          "."
        ]
      }
    },
    {
      "article_id": "abf8edfae0419a81",
      "title": "The Most Joyless Tech Revolution Ever AI Is Making Us Rich and Unhappy",
      "body": "Discomfort around artificial intelligence helps explain the disconnect between a solid economy and an anxious public.",
      "source": "Yahoo",
      "timestamp": "2025-11-22T00:25:57.109774",
      "url": "https://finnhub.io/api/news?id=f5804b00808260a4761f3f621e47fd598f3dc7e0b3c5cb03def8e1509dbe422c",
      "raw_text": "The Most Joyless Tech Revolution Ever AI Is Making Us Rich and Unhappy. Discomfort around artificial intelligence helps explain the disconnect between a solid economy and an anxious public.",
      "tickers_mentioned": "PSA,TECH",
      "sentiment": "neutral",
      "ticker_contexts": {
        "PSA": [],
        "TECH": []
      },
      "features": {
        "entities": {
          "PERSON": [
            "Us Rich",
            "Unhappy"
          ],
          "ORGANIZATION": [
            "Most Joyless Tech Revolution"
          ],
          "GPE": []
        },
        "financial_keywords": {
          "positive": [],
          "negative": [],
          "neutral": []
        },
        "numbers": [],
        "percentages": [],
        "dates": [],
        "top_words": [
          [
            "most",
            1
          ],
          [
            "joyless",
            1
          ],
          [
            "tech",
            1
          ],
          [
            "revolution",
            1
          ],
          [
            "ever",
            1
          ],
          [
            "make",
            1
          ],
          [
            "rich",
            1
          ],
          [
            "unhappy",
            1
          ],
          [
            "discomfort",
            1
          ],
          [
            "around",
            1
          ]
        ],
        "stats": {
          "num_entities": 3,
          "num_positive_keywords": 0,
          "num_negative_keywords": 0,
          "num_neutral_keywords": 0,
          "num_numbers": 0,
          "num_percentages": 0,
          "num_dates": 0
        }
      },
      "tokens": {
        "original": [
          "the",
          "most",
          "joyless",
          "tech",
          "revolution",
          "ever",
          "ai",
          "is",
          "making",
          "us",
          "rich",
          "and",
          "unhappy",
          ".",
          "discomfort",
          "around",
          "artificial",
          "intelligence",
          "helps",
          "explain",
          "the",
          "disconnect",
          "between",
          "a",
          "solid",
          "economy",
          "and",
          "an",
          "anxious",
          "public",
          "."
        ],
        "filtered": [
          "most",
          "joyless",
          "tech",
          "revolution",
          "ever",
          "ai",
          "making",
          "us",
          "rich",
          "unhappy",
          ".",
          "discomfort",
          "around",
          "artificial",
          "intelligence",
          "helps",
          "explain",
          "disconnect",
          "solid",
          "economy",
          "anxious",
          "public",
          "."
        ],
        "lemmatized": [
          "most",
          "joyless",
          "tech",
          "revolution",
          "ever",
          "ai",
          "make",
          "u",
          "rich",
          "unhappy",
          ".",
          "discomfort",
          "around",
          "artificial",
          "intelligence",
          "help",
          "explain",
          "disconnect",
          "solid",
          "economy",
          "anxious",
          "public",
          "."
        ]
      }
    },
    {
      "article_id": "8eeda39e8e2b86de",
      "title": "Harvard now owns nearly half a billion dollars worth of Bitcoin, filings show",
      "body": "The Ivy League school invested more than 20 percent of its U.S.-listed public equity holdings in a crypto ETF.",
      "source": "Yahoo",
      "timestamp": "2025-11-22T00:25:57.216888",
      "url": "https://finnhub.io/api/news?id=1a788c994dae930f4f736344df5812d613fa59d29759dc8f3d867825e9642605",
      "raw_text": "Harvard now owns nearly half a billion dollars worth of Bitcoin, filings show. The Ivy League school invested more than 20 percent of its U.S.-listed public equity holdings in a crypto ETF.",
      "tickers_mentioned": "PSA,EQR",
      "sentiment": "neutral",
      "ticker_contexts": {
        "PSA": [],
        "EQR": []
      },
      "features": {
        "entities": {
          "PERSON": [
            "Harvard"
          ],
          "ORGANIZATION": [
            "Ivy League",
            "ETF"
          ],
          "GPE": [
            "Bitcoin"
          ]
        },
        "financial_keywords": {
          "positive": [],
          "negative": [],
          "neutral": [
            "hold"
          ]
        },
        "numbers": [
          "20"
        ],
        "percentages": [],
        "dates": [],
        "top_words": [
          [
            "harvard",
            1
          ],
          [
            "own",
            1
          ],
          [
            "nearly",
            1
          ],
          [
            "half",
            1
          ],
          [
            "billion",
            1
          ],
          [
            "dollar",
            1
          ],
          [
            "worth",
            1
          ],
          [
            "bitcoin",
            1
          ],
          [
            "filing",
            1
          ],
          [
            "show",
            1
          ]
        ],
        "stats": {
          "num_entities": 4,
          "num_positive_keywords": 0,
          "num_negative_keywords": 0,
          "num_neutral_keywords": 1,
          "num_numbers": 1,
          "num_percentages": 0,
          "num_dates": 0
        }
      },
      "tokens": {
        "original": [
          "harvard",
          "now",
          "owns",
          "nearly",
          "half",
          "a",
          "billion",
          "dollars",
          "worth",
          "of",
          "bitcoin",
          ",",
          "filings",
          "show",
          ".",
          "the",
          "ivy",
          "league",
          "school",
          "invested",
          "more",
          "than",
          "20",
          "percent",
          "of",
          "its",
          "u.s.-listed",
          "public",
          "equity",
          "holdings",
          "in",
          "a",
          "crypto",
          "etf",
          "."
        ],
        "filtered": [
          "harvard",
          "owns",
          "nearly",
          "half",
          "billion",
          "dollars",
          "worth",
          "bitcoin",
          ",",
          "filings",
          "show",
          ".",
          "ivy",
          "league",
          "school",
          "invested",
          "more",
          "20",
          "percent",
          "u.s.-listed",
          "public",
          "equity",
          "holdings",
          "crypto",
          "etf",
          "."
        ],
        "lemmatized": [
          "harvard",
          "own",
          "nearly",
          "half",
          "billion",
          "dollar",
          "worth",
          "bitcoin",
          ",",
          "filing",
          "show",
          ".",
          "ivy",
          "league",
          "school",
          "invest",
          "more",
          "20",
          "percent",
          "u.s.-listed",
          "public",
          "equity",
          "holdings",
          "crypto",
          "etf",
          "."
        ]
      }
    }
  ]
}